file_toolkit/__init__.py
file_toolkit/file_ops.py
file_toolkit/hash_ops.py
file_toolkit/monitor_ops.py
file_toolkit/progress.py
file_toolkit/search_ops.py
file_toolkit/stats_ops.py
file_toolkit/sync_ops.py
file_toolkit/temp_file_utils.py
file_toolkit/zip_ops.py
file_toolkit-0.1.3.dist-info/licenses/LICENSE
file_toolkit-0.1.3.dist-info/METADATA
file_toolkit-0.1.3.dist-info/WHEEL
file_toolkit-0.1.3.dist-info/top_level.txt
file_toolkit-0.1.3.dist-info/RECORD
