Metadata-Version: 2.4
Name: file-toolkit
Version: 0.1.3
Summary: file-toolkit is a complete suite of utilities for manipulating, organizing, and monitoring files and directories in Python. It offers functions for copying, moving, synchronizing, compressing, hashing, advanced searching, temporary file management, and much more, with a focus on productivity, security, and auditing.
Author-email: Thaissa Ferreira <thaissa.teodoro@hotmail.com>
License-Expression: MIT
Classifier: Development Status :: 4 - Beta
Classifier: Intended Audience :: Developers
Classifier: Programming Language :: Python :: 3
Classifier: Operating System :: OS Independent
Classifier: Topic :: Software Development :: Libraries
Requires-Python: >=3.8
License-File: LICENSE
Requires-Dist: logging-metrics>=0.1.2
Provides-Extra: dev
Requires-Dist: pytest>=7.0.0; extra == "dev"
Requires-Dist: pytest-cov>=4.0.0; extra == "dev"
Requires-Dist: pytest-xdist>=3.0.0; extra == "dev"
Requires-Dist: pytest-mock>=3.10.0; extra == "dev"
Requires-Dist: py4j>=0.10.9; extra == "dev"
Requires-Dist: coverage>=6.0.0; extra == "dev"
Requires-Dist: faker>=18.0.0; extra == "dev"
Requires-Dist: hypothesis>=6.0.0; extra == "dev"
Requires-Dist: black>=22.0.0; extra == "dev"
Requires-Dist: flake8>=5.0.0; extra == "dev"
Dynamic: license-file
